simplefilters.py
django_simplefilters-1.0.0.dist-info/LICENSE
django_simplefilters-1.0.0.dist-info/METADATA
django_simplefilters-1.0.0.dist-info/WHEEL
django_simplefilters-1.0.0.dist-info/top_level.txt
django_simplefilters-1.0.0.dist-info/RECORD
