Metadata-Version: 2.1
Name: django-simplefilters
Version: 1.0.0
Summary: Simple drop-in replacement for rest_framework.filters
Home-page: https://github.com/lukaszb/django-simplefilters
Author: Lukasz Balcerzak
Author-email: lukaszbalcerzak@gmail.com
License: MIT
Platform: UNKNOWN
License-File: LICENSE
Requires-Dist: python-dateutil
